setup.py
eezotop_hist_new/__init__.py
eezotop_hist_new/hist.py
eezotop_hist_new.egg-info/PKG-INFO
eezotop_hist_new.egg-info/SOURCES.txt
eezotop_hist_new.egg-info/dependency_links.txt
eezotop_hist_new.egg-info/requires.txt
eezotop_hist_new.egg-info/top_level.txt